fomo/__init__.py
fomo/algorithm.py
fomo/estimator.py
fomo/metrics.py
fomo/problem.py
fomo/surrogate_models.py
fomo/surrogate_problem.py
fomo/utils.py
fomo/version.py
pyfomo-0.0.17.dist-info/LICENSE
pyfomo-0.0.17.dist-info/METADATA
pyfomo-0.0.17.dist-info/WHEEL
pyfomo-0.0.17.dist-info/top_level.txt
pyfomo-0.0.17.dist-info/RECORD
