Metadata-Version: 2.1
Name: pyfomo
Version: 0.0.17
Summary: Fairness oriented Multi-objective Optimization
Home-page: https://github.com/cavalab/fomo
Author: William La Cava
Author-email: williamlacava@gmail.com
Classifier: Programming Language :: Python :: 3
Classifier: License :: OSI Approved :: BSD License
Classifier: Operating System :: OS Independent
Requires-Python: >=3.7
License-File: LICENSE
Requires-Dist: pymoo
Requires-Dist: scikit-learn
Requires-Dist: pandas
Requires-Dist: ipdb
Provides-Extra: docs
Requires-Dist: sphinx ; extra == 'docs'
Requires-Dist: recommonmark ; extra == 'docs'
Requires-Dist: seaborn ; extra == 'docs'
Requires-Dist: nbsphinx ; extra == 'docs'
Requires-Dist: matplotlib ; extra == 'docs'
Requires-Dist: jupyter ; extra == 'docs'
Requires-Dist: sphinx-copybutton ; extra == 'docs'
Requires-Dist: numpydoc ; extra == 'docs'
Requires-Dist: m2r2 ; extra == 'docs'
Requires-Dist: furo ; extra == 'docs'
Requires-Dist: sphinx-design ; extra == 'docs'
Requires-Dist: sphinx-inline-tabs ; extra == 'docs'
Requires-Dist: myst-parser ; extra == 'docs'
